setup.py
Products/__init__.py
Products.References.egg-info/PKG-INFO
Products.References.egg-info/SOURCES.txt
Products.References.egg-info/dependency_links.txt
Products.References.egg-info/namespace_packages.txt
Products.References.egg-info/not-zip-safe
Products.References.egg-info/top_level.txt
Products/References/README.txt
Products/References/Reference.gif
Products/References/VERSION.txt
Products/References/__init__.py
Products/References/addForm.dtml
Products/References/editForm.dtml
Products/References/tests.py