Metadata-Version: 1.0
Name: Products.References
Version: 1.0
Summary: References to Zope objects for Zope 2.10 (or above)
Home-page: http://pypi.python.org/pypi/Products.References
Author: Dieter Maurer
Author-email: dieter@handshake.de
License: BSD
Keywords: Zope 2,reference,symbolic link
Platform: UNKNOWN
Classifier: Development Status :: 5 - Production/Stable
Classifier: Intended Audience :: Developers
Classifier: License :: OSI Approved :: BSD License
Classifier: Framework :: Zope2
Classifier: Operating System :: OS Independent
Classifier: Programming Language :: Python
Classifier: Topic :: Utilities
